matrx_dream_service/__init__.py
matrx_dream_service/cli.py
matrx_dream_service/matrx_microservice/__init__.py
matrx_dream_service/matrx_microservice/contents.py
matrx_dream_service/matrx_microservice/default_template.py
matrx_dream_service/matrx_microservice/generator.py
matrx_dream_service/matrx_microservice/github_utils.py
matrx_dream_service/matrx_microservice/merge_config.py
matrx_dream_service-1.0.4.dist-info/METADATA
matrx_dream_service-1.0.4.dist-info/WHEEL
matrx_dream_service-1.0.4.dist-info/entry_points.txt
matrx_dream_service-1.0.4.dist-info/top_level.txt
matrx_dream_service-1.0.4.dist-info/RECORD
