Metadata-Version: 2.4
Name: matrx-dream-service
Version: 1.0.4
Summary: Matrx service
Requires-Python: >=3.10
Requires-Dist: black>=25.1.0
Requires-Dist: githubkit>=0.12.16
Requires-Dist: matrx-utils>=1.0.2
